ControlBurn/ControlBurnInterpret.py
ControlBurn/ControlBurnModel.py
ControlBurn/__init__.py
ControlBurn-0.1.3.dist-info/LICENSE
ControlBurn-0.1.3.dist-info/METADATA
ControlBurn-0.1.3.dist-info/WHEEL
ControlBurn-0.1.3.dist-info/top_level.txt
ControlBurn-0.1.3.dist-info/RECORD
