Metadata-Version: 2.1
Name: ControlBurn
Version: 0.1.3
Summary: Feature Selection by Sparse Forests
Home-page: https://github.com/brianliu12437/ControlBurnPackage
Author: Brian Liu
Author-email: briliu@mit.edu
Project-URL: Bug Tracker, https://github.com/brianliu12437/ControlBurnPackage/issues
Classifier: Programming Language :: Python :: 3
Classifier: License :: OSI Approved :: MIT License
Classifier: Operating System :: OS Independent
Requires-Python: >=3.6
License-File: LICENSE
